maclidsensor/__init__.py
maclidsensor/constants.py
maclidsensor/exceptions.py
maclidsensor/sensor.py
maclidsensor-1.0.3.dist-info/licenses/LICENSE
maclidsensor-1.0.3.dist-info/METADATA
maclidsensor-1.0.3.dist-info/WHEEL
maclidsensor-1.0.3.dist-info/entry_points.txt
maclidsensor-1.0.3.dist-info/top_level.txt
maclidsensor-1.0.3.dist-info/RECORD
