Metadata-Version: 2.4
Name: maclidsensor
Version: 1.0.3
Summary: A python package to read macbook lid angle.
Author-email: Yashwan Kafle <yashwankafle@gmail.com>
License: MIT License
Project-URL: Homepage, https://github.com/YashwanKafle/maclidsensor
Keywords: maclidsensor
Requires-Python: >=3.8
License-File: LICENSE
Requires-Dist: hidapi==0.14.0.post4
Provides-Extra: all
Requires-Dist: maclidsensor[extra]; extra == "all"
Dynamic: license-file
